cloudy_with_a_chance_of_meatballs_cdk_lambda_token_authorizer_jwt/__init__.py
cloudy_with_a_chance_of_meatballs_cdk_lambda_token_authorizer_jwt/py.typed
cloudy_with_a_chance_of_meatballs_cdk_lambda_token_authorizer_jwt/_jsii/__init__.py
cloudy_with_a_chance_of_meatballs_cdk_lambda_token_authorizer_jwt/_jsii/cdk-lambda-token-authorizer-jwt@0.1.24.jsii.tgz
cloudy_with_a_chance_of_meatballs.cdk_lambda_token_authorizer_jwt-0.1.24.dist-info/LICENSE
cloudy_with_a_chance_of_meatballs.cdk_lambda_token_authorizer_jwt-0.1.24.dist-info/METADATA
cloudy_with_a_chance_of_meatballs.cdk_lambda_token_authorizer_jwt-0.1.24.dist-info/WHEEL
cloudy_with_a_chance_of_meatballs.cdk_lambda_token_authorizer_jwt-0.1.24.dist-info/top_level.txt
cloudy_with_a_chance_of_meatballs.cdk_lambda_token_authorizer_jwt-0.1.24.dist-info/RECORD
