Metadata-Version: 2.1
Name: cloudy-with-a-chance-of-meatballs.cdk-lambda-token-authorizer-jwt
Version: 0.1.24
Summary: Add a lambda function to your aws-rest-api-gateway which can be used as a token authorizer
Home-page: https://github.com/cloudy-with-a-chance-of-meatballs/cdk-lambda-token-authorizer-jwt.git
Author: cfuerst<c.fuerst@gmail.com>
License: MIT
Project-URL: Source, https://github.com/cloudy-with-a-chance-of-meatballs/cdk-lambda-token-authorizer-jwt.git
Classifier: Intended Audience :: Developers
Classifier: Operating System :: OS Independent
Classifier: Programming Language :: JavaScript
Classifier: Programming Language :: Python :: 3 :: Only
Classifier: Programming Language :: Python :: 3.8
Classifier: Programming Language :: Python :: 3.9
Classifier: Programming Language :: Python :: 3.10
Classifier: Programming Language :: Python :: 3.11
Classifier: Typing :: Typed
Classifier: Development Status :: 4 - Beta
Classifier: License :: OSI Approved
Requires-Python: ~=3.8
License-File: LICENSE
Requires-Dist: aws-cdk-lib <3.0.0,>=2.5.0
Requires-Dist: constructs <11.0.0,>=10.0.5
Requires-Dist: jsii <2.0.0,>=1.99.0
Requires-Dist: publication >=0.0.3
Requires-Dist: typeguard ~=2.13.3
